k2db/__init__.py
k2db/lathe.py
k2db/candidate_network/__init__.py
k2db/candidate_network/candidate_network.py
k2db/candidate_network/candidate_network_handler.py
k2db/database/__init__.py
k2db/database/database_handler.py
k2db/database/database_iter.py
k2db/evaluation/__init__.py
k2db/evaluation/evaluation_handler.py
k2db/index/__init__.py
k2db/index/babel_hash.py
k2db/index/index_handler.py
k2db/index/schema_graph.py
k2db/index/schema_index.py
k2db/index/value_index.py
k2db/keyword_match/__init__.py
k2db/keyword_match/keyword_match.py
k2db/keyword_match/keyword_match_handler.py
k2db/query_match/__init__.py
k2db/query_match/query_match.py
k2db/query_match/query_match_handler.py
k2db/utils/__init__.py
k2db/utils/config_handler.py
k2db/utils/graph.py
k2db/utils/lathe_result.py
k2db/utils/logger.py
k2db/utils/memory.py
k2db/utils/next_path.py
k2db/utils/plots.py
k2db/utils/similarity.py
k2db/utils/tf_iaf.py
k2db/utils/timestr.py
k2db/utils/tokenizer.py
k2db/utils/truncate.py
k2db-0.0.4.dist-info/LICENSE
k2db-0.0.4.dist-info/METADATA
k2db-0.0.4.dist-info/WHEEL
k2db-0.0.4.dist-info/top_level.txt
k2db-0.0.4.dist-info/RECORD
