Metadata-Version: 2.1
Name: k2db
Version: 0.0.4
Summary: Keyword Search over Relational Databases
Home-page: https://github.com/pr3martins/K2D
Author: Paulo Martins
Author-email: pr3martins@gmail.com
License: UNKNOWN
Project-URL: Bug Tracker, https://github.com/pr3martins/K2D/issues
Platform: UNKNOWN
Classifier: Programming Language :: Python :: 3
Classifier: License :: OSI Approved :: GNU General Public License v3 (GPLv3)
Classifier: Operating System :: OS Independent
Requires-Python: >=3.6
License-File: LICENSE
Requires-Dist: nltk
Requires-Dist: psutil
Requires-Dist: psycopg2-binary
Requires-Dist: matplotlib
Requires-Dist: prettytable
